py.typed
livepeer/__init__.py
livepeer/_hooks/__init__.py
livepeer/_hooks/registration.py
livepeer/_hooks/sdkhooks.py
livepeer/_hooks/types.py
livepeer/accesscontrol.py
livepeer/asset.py
livepeer/basesdk.py
livepeer/generate.py
livepeer/httpclient.py
livepeer/metrics.py
livepeer/models/components/__init__.py
livepeer/models/components/apierror.py
livepeer/models/components/asset.py
livepeer/models/components/asset_patch_payload.py
livepeer/models/components/attestation.py
livepeer/models/components/body_genaudiototext.py
livepeer/models/components/body_genimagetoimage.py
livepeer/models/components/body_genimagetovideo.py
livepeer/models/components/body_gensegmentanything2.py
livepeer/models/components/body_genupscale.py
livepeer/models/components/chunk.py
livepeer/models/components/clip_payload.py
livepeer/models/components/create_room_response.py
livepeer/models/components/creator_id.py
livepeer/models/components/encryption.py
livepeer/models/components/encryption_output.py
livepeer/models/components/export_task_params.py
livepeer/models/components/ffmpeg_profile.py
livepeer/models/components/get_room_user_response.py
livepeer/models/components/httpmetadata.py
livepeer/models/components/imageresponse.py
livepeer/models/components/input_creator_id.py
livepeer/models/components/ipfs_export_params.py
livepeer/models/components/ipfs_file_info.py
livepeer/models/components/masksresponse.py
livepeer/models/components/media.py
livepeer/models/components/multistream.py
livepeer/models/components/multistream_target.py
livepeer/models/components/multistream_target_input.py
livepeer/models/components/multistream_target_patch_payload.py
livepeer/models/components/new_asset_from_url_payload.py
livepeer/models/components/new_asset_payload.py
livepeer/models/components/new_stream_payload.py
livepeer/models/components/playback_info.py
livepeer/models/components/playback_policy.py
livepeer/models/components/pull.py
livepeer/models/components/realtime_viewership_metric.py
livepeer-0.3.0.dist-info/METADATA
livepeer-0.3.0.dist-info/WHEEL
livepeer-0.3.0.dist-info/RECORD
